ssos/__init__.py
ssos/__main__.py
ssos/core.py
ssos/default.ssos
ssos/filt.py
ssos/ins.py
ssos/opt.py
ssos/utils.py
ssos/semp/default.nnw
ssos/semp/gauss_2.5_5x5.conv
ssos/semp/ssos.param
ssos/semp/ssos.scamp
ssos/semp/ssos.sex
ssos/semp/ssos.swarp
ssos-1.3.4.dist-info/LICENSE
ssos-1.3.4.dist-info/METADATA
ssos-1.3.4.dist-info/WHEEL
ssos-1.3.4.dist-info/entry_points.txt
ssos-1.3.4.dist-info/top_level.txt
ssos-1.3.4.dist-info/RECORD
