Metadata-Version: 2.1
Name: ssos
Version: 1.3.4
Summary: The ssos Pipeline - Detection of Solar System Objects in astronomical images
Home-page: https://github.com/maxmahlke/ssos
Author: Max Mahlke
Author-email: max.mahlke@oca.eu
License: UNKNOWN
Keywords: astronomy astrophysics solar-system data pipeline
Platform: UNKNOWN
Requires-Python: >=3.6
Requires-Dist: astropy
Requires-Dist: matplotlib
Requires-Dist: numpy
Requires-Dist: pandas (>=0.23.0)
Requires-Dist: scipy
Requires-Dist: statsmodels (>=0.9.0)
Requires-Dist: tqdm (>=4.40.2)
